async_pyarrow/Flight_pb2.py
async_pyarrow/Flight_pb2_grpc.py
async_pyarrow/__init__.py
async_pyarrow/flight.py
async_pyarrow-0.2.0.dist-info/METADATA
async_pyarrow-0.2.0.dist-info/WHEEL
async_pyarrow-0.2.0.dist-info/top_level.txt
async_pyarrow-0.2.0.dist-info/RECORD
