Metadata-Version: 2.1
Name: async-pyarrow
Version: 0.2.0
Requires-Dist: pyarrow
Requires-Dist: grpcio
Requires-Dist: protobuf
